{"0307883b5d063703-A\u00e7a\u00ed": "Yhat_var", "0307883b5d063703-Cassava": "BaggingRegressor", "0307883b5d063703-Livestock": "BaggingRegressor", "0307883b5d063703-Others-permanent": "DecisionTreeRegressor", "0307883b5d063703-Others-temporary": "MLPRegressor", "03e477d4ede00e89-Beans": "AdaBoostRegressor", "03e477d4ede00e89-Cassava": "BaggingRegressor", "03e477d4ede00e89-Corn": "MLPRegressor", "03e477d4ede00e89-Livestock": "Yhat_sarimax", "03e477d4ede00e89-Others-permanent": "Yhat_AutoReg", "03e477d4ede00e89-Others-temporary": "PoissonRegressor", "03e477d4ede00e89-Rice": "Yhat_sarimax", "051e9cc7d7636816-A\u00e7a\u00ed": "Yhat_var", "051e9cc7d7636816-Beans": "SVR", "051e9cc7d7636816-Cassava": "DecisionTreeRegressor", "051e9cc7d7636816-Cocoa": "SVR", "051e9cc7d7636816-Corn": "Yhat_sarimax", "051e9cc7d7636816-Livestock": "Yhat_var", "051e9cc7d7636816-Others-permanent": "LassoLars", "051e9cc7d7636816-Others-temporary": "LassoLars", "051e9cc7d7636816-Rice": "TheilSenRegressor", "062ce4c17e84291e-Cassava": "Yhat_var", "062ce4c17e84291e-Livestock": "DummyRegressor", "062ce4c17e84291e-Others-permanent": "Yhat_autoarima", "062ce4c17e84291e-Others-temporary": "AdaBoostRegressor", "074590cfc1c41ebf-A\u00e7a\u00ed": "AdaBoostRegressor", "074590cfc1c41ebf-Beans": "Yhat_sarimax", "074590cfc1c41ebf-Cassava": "GradientBoostingRegressor", "074590cfc1c41ebf-Cocoa": "Yhat_sarimax", "074590cfc1c41ebf-Corn": "AdaBoostRegressor", "074590cfc1c41ebf-Livestock": "Yhat_AutoReg", "074590cfc1c41ebf-Others-permanent": "HistGradientBoostingRegressor", "074590cfc1c41ebf-Others-temporary": "AdaBoostRegressor", "074590cfc1c41ebf-Rice": "GaussianProcessRegressor", "074590cfc1c41ebf-Soy": "OrthogonalMatchingPursuit", "07bba1a59af78f2d-A\u00e7a\u00ed": "PoissonRegressor", "07bba1a59af78f2d-Beans": "Yhat_AutoReg", "07bba1a59af78f2d-Cassava": "DecisionTreeRegressor", "07bba1a59af78f2d-Corn": "BaggingRegressor", "07bba1a59af78f2d-Livestock": "PoissonRegressor", "07bba1a59af78f2d-Others-permanent": "TheilSenRegressor", "07bba1a59af78f2d-Others-temporary": "PoissonRegressor", "07bba1a59af78f2d-Palm oil": "LinearSVR", "07bba1a59af78f2d-Rice": "BaggingRegressor", "07ce2e79e19977e9-A\u00e7a\u00ed": "AdaBoostRegressor", "07ce2e79e19977e9-Cassava": "Yhat_sarimax", "07ce2e79e19977e9-Corn": "PassiveAggressiveRegressor", "07ce2e79e19977e9-Livestock": "TweedieRegressor", "07ce2e79e19977e9-Others-permanent": "AdaBoostRegressor", "07ce2e79e19977e9-Others-temporary": "DecisionTreeRegressor", "07ed828db19fe8ca-Beans": "MLPRegressor", "07ed828db19fe8ca-Cassava": "BayesianRidge", "07ed828db19fe8ca-Corn": "Yhat_sarimax", "07ed828db19fe8ca-Livestock": "Yhat_autoarima", "07ed828db19fe8ca-Others-permanent": "PassiveAggressiveRegressor", "07ed828db19fe8ca-Others-temporary": "BaggingRegressor", "07ed828db19fe8ca-Rice": "GaussianProcessRegressor", "09791645137aa877-Livestock": "Yhat_autoarima", "09791645137aa877-Others-permanent": "Yhat_AutoReg", "09791645137aa877-Others-temporary": "AdaBoostRegressor", "0dcbfaab30eb40c1-A\u00e7a\u00ed": "MLPRegressor", "0dcbfaab30eb40c1-Beans": "GradientBoostingRegressor", "0dcbfaab30eb40c1-Cassava": "LinearRegression", "0dcbfaab30eb40c1-Corn": "Yhat_autoarima", "0dcbfaab30eb40c1-Livestock": "Yhat_AutoReg", "0dcbfaab30eb40c1-Others-permanent": "Yhat_autoarima", "0dcbfaab30eb40c1-Others-temporary": "LinearSVR", "0dcbfaab30eb40c1-Rice": "DecisionTreeRegressor", "0ea136556d12fc16-Beans": "ElasticNet", "0ea136556d12fc16-Cassava": "Yhat_autoarima", "0ea136556d12fc16-Cocoa": "AdaBoostRegressor", "0ea136556d12fc16-Corn": "GaussianProcessRegressor", "0ea136556d12fc16-Livestock": "Yhat_autoarima", "0ea136556d12fc16-Others-permanent": "DecisionTreeRegressor", "0ea136556d12fc16-Others-temporary": "AdaBoostRegressor", "0ea136556d12fc16-Rice": "ExtraTreesRegressor", "1096f26c5a236d0b-Beans": "PoissonRegressor", "1096f26c5a236d0b-Cassava": "PoissonRegressor", "1096f26c5a236d0b-Corn": "LinearRegression", "1096f26c5a236d0b-Livestock": "Yhat_AutoReg", "1096f26c5a236d0b-Others-permanent": "AdaBoostRegressor", "1096f26c5a236d0b-Others-temporary": "MLPRegressor", "10973d6049af898b-A\u00e7a\u00ed": "AdaBoostRegressor", "10973d6049af898b-Beans": "MLPRegressor", "10973d6049af898b-Cassava": "AdaBoostRegressor", "10973d6049af898b-Corn": "Yhat_var", "10973d6049af898b-Livestock": "AdaBoostRegressor", "10973d6049af898b-Others-permanent": "MLPRegressor", "10973d6049af898b-Others-temporary": "DummyRegressor", "10973d6049af898b-Rice": "Yhat_AutoReg", "10973d6049af898b-Soy": "DecisionTreeRegressor", "114487007645c940-A\u00e7a\u00ed": "TheilSenRegressor", "114487007645c940-Beans": "Yhat_sarimax", "114487007645c940-Cassava": "SVR", "114487007645c940-Corn": "RandomForestRegressor", "114487007645c940-Livestock": "PoissonRegressor", "114487007645c940-Others-permanent": "Yhat_autoarima", "114487007645c940-Others-temporary": "NuSVR", "114487007645c940-Rice": "BaggingRegressor", "11645a57d3a1d507-A\u00e7a\u00ed": "Yhat_var", "11645a57d3a1d507-Beans": "Yhat_autoarima", "11645a57d3a1d507-Cassava": "Yhat_sarimax", "11645a57d3a1d507-Cocoa": "GaussianProcessRegressor", "11645a57d3a1d507-Corn": "AdaBoostRegressor", "11645a57d3a1d507-Livestock": "Yhat_autoarima", "11645a57d3a1d507-Others-permanent": "GaussianProcessRegressor", "11645a57d3a1d507-Others-temporary": "GaussianProcessRegressor", "11645a57d3a1d507-Palm oil": "Yhat_AutoReg", "11b6622567f98f3b-Beans": "AdaBoostRegressor", "11b6622567f98f3b-Cassava": "PoissonRegressor", "11b6622567f98f3b-Corn": "MLPRegressor", "11b6622567f98f3b-Livestock": "Yhat_AutoReg", "11b6622567f98f3b-Others-permanent": "LinearSVR", "11b6622567f98f3b-Others-temporary": "BaggingRegressor", "11b6622567f98f3b-Palm oil": "AdaBoostRegressor", "13804a196311e1ba-A\u00e7a\u00ed": "MLPRegressor", "13804a196311e1ba-Beans": "Yhat_autoarima", "13804a196311e1ba-Cassava": "AdaBoostRegressor", "13804a196311e1ba-Cocoa": "KernelRidge", "13804a196311e1ba-Corn": "DecisionTreeRegressor", "13804a196311e1ba-Livestock": "PassiveAggressiveRegressor", "13804a196311e1ba-Others-permanent": "Yhat_autoarima", "13804a196311e1ba-Others-temporary": "Yhat_var", "13804a196311e1ba-Rice": "GaussianProcessRegressor", "164c8953d3af2bbe-A\u00e7a\u00ed": "AdaBoostRegressor", "164c8953d3af2bbe-Beans": "DecisionTreeRegressor", "164c8953d3af2bbe-Cassava": "RandomForestRegressor", "164c8953d3af2bbe-Cocoa": "Yhat_autoarima", "164c8953d3af2bbe-Corn": "Yhat_AutoReg", "164c8953d3af2bbe-Livestock": "Yhat_sarimax", "164c8953d3af2bbe-Others-permanent": "Yhat_AutoReg", "164c8953d3af2bbe-Others-temporary": "DecisionTreeRegressor", "164c8953d3af2bbe-Rice": "Yhat_sarimax", "18e37d24ff8517ef-Beans": "BaggingRegressor", "18e37d24ff8517ef-Cassava": "Yhat_var", "18e37d24ff8517ef-Corn": "PoissonRegressor", "18e37d24ff8517ef-Livestock": "ExtraTreesRegressor", "18e37d24ff8517ef-Others-permanent": "NuSVR", "18e37d24ff8517ef-Others-temporary": "Yhat_AutoReg", "18e37d24ff8517ef-Rice": "GaussianProcessRegressor", "18e37d24ff8517ef-Soy": "AdaBoostRegressor", "18fb5197aa553b9c-Beans": "GaussianProcessRegressor", "18fb5197aa553b9c-Cassava": "AdaBoostRegressor", "18fb5197aa553b9c-Corn": "GradientBoostingRegressor", "18fb5197aa553b9c-Livestock": "Yhat_autoarima", "18fb5197aa553b9c-Others-permanent": "KernelRidge", "18fb5197aa553b9c-Others-temporary": "Yhat_sarimax", "1bd7145ed1da044a-A\u00e7a\u00ed": "AdaBoostRegressor", "1bd7145ed1da044a-Beans": "GaussianProcessRegressor", "1bd7145ed1da044a-Cassava": "Yhat_autoarima", "1bd7145ed1da044a-Cocoa": "MLPRegressor", "1bd7145ed1da044a-Corn": "PassiveAggressiveRegressor", "1bd7145ed1da044a-Livestock": "TweedieRegressor", "1bd7145ed1da044a-Others-permanent": "ElasticNet", "1bd7145ed1da044a-Others-temporary": "DecisionTreeRegressor", "1bd7145ed1da044a-Rice": "Yhat_sarimax", "1bd7145ed1da044a-Soy": "TheilSenRegressor", "1d8a692643f9a15a-A\u00e7a\u00ed": "AdaBoostRegressor", "1d8a692643f9a15a-Beans": "Yhat_var", "1d8a692643f9a15a-Cassava": "Yhat_autoarima", "1d8a692643f9a15a-Cocoa": "LinearSVR", "1d8a692643f9a15a-Corn": "AdaBoostRegressor", "1d8a692643f9a15a-Livestock": "LinearSVR", "1d8a692643f9a15a-Others-permanent": "Yhat_AutoReg", "1d8a692643f9a15a-Others-temporary": "AdaBoostRegressor", "1d8a692643f9a15a-Rice": "SVR", "20589298110cd872-A\u00e7a\u00ed": "Yhat_var", "20589298110cd872-Beans": "ElasticNet", "20589298110cd872-Cassava": "AdaBoostRegressor", "20589298110cd872-Corn": "Ridge", "20589298110cd872-Livestock": "Yhat_sarimax", "20589298110cd872-Others-permanent": "AdaBoostRegressor", "20589298110cd872-Others-temporary": "NuSVR", "20589298110cd872-Rice": "GaussianProcessRegressor", "20589298110cd872-Soy": "PoissonRegressor", "205ccde9be499e17-A\u00e7a\u00ed": "PassiveAggressiveRegressor", "205ccde9be499e17-Beans": "MLPRegressor", "205ccde9be499e17-Cassava": "NuSVR", "205ccde9be499e17-Cocoa": "LinearSVR", "205ccde9be499e17-Corn": "MLPRegressor", "205ccde9be499e17-Livestock": "AdaBoostRegressor", "205ccde9be499e17-Others-permanent": "AdaBoostRegressor", "205ccde9be499e17-Others-temporary": "Yhat_AutoReg", "205ccde9be499e17-Palm oil": "Yhat_AutoReg", "205ccde9be499e17-Rice": "DecisionTreeRegressor", "20e241460ce4140d-A\u00e7a\u00ed": "GaussianProcessRegressor", "20e241460ce4140d-Cassava": "PoissonRegressor", "20e241460ce4140d-Livestock": "HistGradientBoostingRegressor", "20e241460ce4140d-Others-permanent": "Yhat_autoarima", "20e241460ce4140d-Others-temporary": "KernelRidge", "20e241460ce4140d-Rice": "PassiveAggressiveRegressor", "2631530645ac2ec8-A\u00e7a\u00ed": "AdaBoostRegressor", "2631530645ac2ec8-Beans": "Lars", "2631530645ac2ec8-Cassava": "Yhat_AutoReg", "2631530645ac2ec8-Cocoa": "PoissonRegressor", "2631530645ac2ec8-Corn": "AdaBoostRegressor", "2631530645ac2ec8-Livestock": "PassiveAggressiveRegressor", "2631530645ac2ec8-Others-permanent": "PoissonRegressor", "2631530645ac2ec8-Others-temporary": "GaussianProcessRegressor", "2631530645ac2ec8-Palm oil": "PoissonRegressor", "2a6b10e6e68be90e-A\u00e7a\u00ed": "PassiveAggressiveRegressor", "2a6b10e6e68be90e-Beans": "GaussianProcessRegressor", "2a6b10e6e68be90e-Cassava": "BaggingRegressor", "2a6b10e6e68be90e-Cocoa": "AdaBoostRegressor", "2a6b10e6e68be90e-Corn": "NuSVR", "2a6b10e6e68be90e-Livestock": "Yhat_autoarima", "2a6b10e6e68be90e-Others-permanent": "BaggingRegressor", "2a6b10e6e68be90e-Others-temporary": "Yhat_sarimax", "2a6b10e6e68be90e-Soy": "AdaBoostRegressor", "2ad055c7757d499d-A\u00e7a\u00ed": "LinearSVR", "2ad055c7757d499d-Beans": "AdaBoostRegressor", "2ad055c7757d499d-Cassava": "Yhat_autoarima", "2ad055c7757d499d-Cocoa": "LassoLars", "2ad055c7757d499d-Corn": "Yhat_autoarima", "2ad055c7757d499d-Livestock": "PoissonRegressor", "2ad055c7757d499d-Others-permanent": "SVR", "2ad055c7757d499d-Others-temporary": "Yhat_autoarima", "2ad055c7757d499d-Palm oil": "Yhat_AutoReg", "2ad055c7757d499d-Rice": "RandomForestRegressor", "351174f21316c2f0-A\u00e7a\u00ed": "LinearSVR", "351174f21316c2f0-Beans": "LassoLars", "351174f21316c2f0-Cassava": "LinearRegression", "351174f21316c2f0-Cocoa": "AdaBoostRegressor", "351174f21316c2f0-Corn": "Yhat_autoarima", "351174f21316c2f0-Livestock": "Yhat_AutoReg", "351174f21316c2f0-Others-permanent": "BaggingRegressor", "351174f21316c2f0-Others-temporary": "AdaBoostRegressor", "351174f21316c2f0-Rice": "BaggingRegressor", "351bc0cbcce79ec9-A\u00e7a\u00ed": "TheilSenRegressor", "351bc0cbcce79ec9-Beans": "GradientBoostingRegressor", "351bc0cbcce79ec9-Cassava": "DecisionTreeRegressor", "351bc0cbcce79ec9-Cocoa": "PoissonRegressor", "351bc0cbcce79ec9-Corn": "Yhat_AutoReg", "351bc0cbcce79ec9-Livestock": "PassiveAggressiveRegressor", "351bc0cbcce79ec9-Others-permanent": "BaggingRegressor", "351bc0cbcce79ec9-Others-temporary": "AdaBoostRegressor", "351bc0cbcce79ec9-Rice": "AdaBoostRegressor", "3a5d0e5eb1691b38-A\u00e7a\u00ed": "GaussianProcessRegressor", "3a5d0e5eb1691b38-Beans": "Yhat_AutoReg", "3a5d0e5eb1691b38-Cassava": "BayesianRidge", "3a5d0e5eb1691b38-Corn": "PoissonRegressor", "3a5d0e5eb1691b38-Livestock": "BayesianRidge", "3a5d0e5eb1691b38-Others-permanent": "AdaBoostRegressor", "3a5d0e5eb1691b38-Others-temporary": "GaussianProcessRegressor", "3a5d0e5eb1691b38-Rice": "RandomForestRegressor", "3a8618990d23351f-Beans": "GaussianProcessRegressor", "3a8618990d23351f-Cassava": "Yhat_autoarima", "3a8618990d23351f-Corn": "PassiveAggressiveRegressor", "3a8618990d23351f-Livestock": "Yhat_sarimax", "3a8618990d23351f-Others-permanent": "GaussianProcessRegressor", "3a8618990d23351f-Others-temporary": "PoissonRegressor", "3a8618990d23351f-Rice": "GaussianProcessRegressor", "3cf541a13002d37b-A\u00e7a\u00ed": "AdaBoostRegressor", "3cf541a13002d37b-Beans": "GaussianProcessRegressor", "3cf541a13002d37b-Cassava": "Yhat_AutoReg", "3cf541a13002d37b-Cocoa": "Yhat_var", "3cf541a13002d37b-Corn": "LinearRegression", "3cf541a13002d37b-Livestock": "Yhat_AutoReg", "3cf541a13002d37b-Others-permanent": "PoissonRegressor", "3cf541a13002d37b-Others-temporary": "LinearSVR", "3cf541a13002d37b-Rice": "Yhat_AutoReg", "3fdbc27a4bed0deb-A\u00e7a\u00ed": "AdaBoostRegressor", "3fdbc27a4bed0deb-Beans": "RandomForestRegressor", "3fdbc27a4bed0deb-Cassava": "AdaBoostRegressor", "3fdbc27a4bed0deb-Cocoa": "AdaBoostRegressor", "3fdbc27a4bed0deb-Corn": "GaussianProcessRegressor", "3fdbc27a4bed0deb-Livestock": "Yhat_var", "3fdbc27a4bed0deb-Others-permanent": "AdaBoostRegressor", "3fdbc27a4bed0deb-Others-temporary": "DecisionTreeRegressor", "3fdbc27a4bed0deb-Rice": "GaussianProcessRegressor", "40abcc3eff7bcf73-Beans": "TheilSenRegressor", "40abcc3eff7bcf73-Cassava": "AdaBoostRegressor", "40abcc3eff7bcf73-Corn": "RandomForestRegressor", "40abcc3eff7bcf73-Livestock": "Yhat_AutoReg", "40abcc3eff7bcf73-Others-permanent": "LinearSVR", "40abcc3eff7bcf73-Others-temporary": "GaussianProcessRegressor", "40abcc3eff7bcf73-Rice": "PassiveAggressiveRegressor", "41e0f8ccfe523e0d-A\u00e7a\u00ed": "GaussianProcessRegressor", "41e0f8ccfe523e0d-Beans": "MLPRegressor", "41e0f8ccfe523e0d-Cassava": "SVR", "41e0f8ccfe523e0d-Corn": "AdaBoostRegressor", "41e0f8ccfe523e0d-Livestock": "LinearSVR", "41e0f8ccfe523e0d-Others-permanent": "BaggingRegressor", "41e0f8ccfe523e0d-Others-temporary": "GaussianProcessRegressor", "41e0f8ccfe523e0d-Palm oil": "AdaBoostRegressor", "41e0f8ccfe523e0d-Rice": "BaggingRegressor", "437130e27b6165ec-A\u00e7a\u00ed": "AdaBoostRegressor", "437130e27b6165ec-Beans": "LassoLars", "437130e27b6165ec-Cassava": "AdaBoostRegressor", "437130e27b6165ec-Corn": "BaggingRegressor", "437130e27b6165ec-Livestock": "LinearRegression", "437130e27b6165ec-Others-permanent": "Yhat_autoarima", "437130e27b6165ec-Others-temporary": "GaussianProcessRegressor", "437130e27b6165ec-Rice": "PoissonRegressor", "44d800c11a5f3bfa-A\u00e7a\u00ed": "Yhat_var", "44d800c11a5f3bfa-Cassava": "DecisionTreeRegressor", "44d800c11a5f3bfa-Cocoa": "Yhat_autoarima", "44d800c11a5f3bfa-Corn": "AdaBoostRegressor", "44d800c11a5f3bfa-Livestock": "KernelRidge", "44d800c11a5f3bfa-Others-permanent": "LinearSVR", "44d800c11a5f3bfa-Others-temporary": "AdaBoostRegressor", "44d800c11a5f3bfa-Rice": "BaggingRegressor", "47564ef7b8c69829-Beans": "GaussianProcessRegressor", "47564ef7b8c69829-Cassava": "AdaBoostRegressor", "47564ef7b8c69829-Cocoa": "Yhat_sarimax", "47564ef7b8c69829-Corn": "BaggingRegressor", "47564ef7b8c69829-Livestock": "Yhat_autoarima", "47564ef7b8c69829-Others-permanent": "RandomForestRegressor", "47564ef7b8c69829-Others-temporary": "TheilSenRegressor", "47564ef7b8c69829-Rice": "Yhat_autoarima", "480b0f80325080af-Beans": "BaggingRegressor", "480b0f80325080af-Cassava": "LinearSVR", "480b0f80325080af-Cocoa": "LassoLars", "480b0f80325080af-Corn": "KernelRidge", "480b0f80325080af-Livestock": "Yhat_sarimax", "480b0f80325080af-Others-permanent": "TheilSenRegressor", "480b0f80325080af-Others-temporary": "NuSVR", "480b0f80325080af-Rice": "Yhat_autoarima", "480b0f80325080af-Soy": "Yhat_AutoReg", "4b530007d167bd54-A\u00e7a\u00ed": "AdaBoostRegressor", "4b530007d167bd54-Beans": "AdaBoostRegressor", "4b530007d167bd54-Cassava": "DecisionTreeRegressor", "4b530007d167bd54-Corn": "PoissonRegressor", "4b530007d167bd54-Livestock": "BaggingRegressor", "4b530007d167bd54-Others-permanent": "Yhat_AutoReg", "4b530007d167bd54-Others-temporary": "Yhat_autoarima", "4b530007d167bd54-Rice": "AdaBoostRegressor", "4c4428f2e4550a5a-A\u00e7a\u00ed": "MLPRegressor", "4c4428f2e4550a5a-Beans": "RandomForestRegressor", "4c4428f2e4550a5a-Cassava": "RandomForestRegressor", "4c4428f2e4550a5a-Corn": "Yhat_autoarima", "4c4428f2e4550a5a-Livestock": "Yhat_AutoReg", "4c4428f2e4550a5a-Others-permanent": "NuSVR", "4c4428f2e4550a5a-Others-temporary": "PassiveAggressiveRegressor", "4c4428f2e4550a5a-Rice": "DecisionTreeRegressor", "4de42e351006a2ae-Cassava": "AdaBoostRegressor", "4de42e351006a2ae-Livestock": "TheilSenRegressor", "4de42e351006a2ae-Others-permanent": "NuSVR", "4de42e351006a2ae-Others-temporary": "AdaBoostRegressor", "505ceb6546aa8435-A\u00e7a\u00ed": "PassiveAggressiveRegressor", "505ceb6546aa8435-Cocoa": "KernelRidge", "505ceb6546aa8435-Livestock": "Yhat_autoarima", "505ceb6546aa8435-Others-permanent": "AdaBoostRegressor", "505ceb6546aa8435-Others-temporary": "AdaBoostRegressor", "505ceb6546aa8435-Palm oil": "AdaBoostRegressor", "50a2afbdc678a65f-Beans": "PoissonRegressor", "50a2afbdc678a65f-Cassava": "Yhat_sarimax", "50a2afbdc678a65f-Cocoa": "Yhat_autoarima", "50a2afbdc678a65f-Corn": "TheilSenRegressor", "50a2afbdc678a65f-Livestock": "AdaBoostRegressor", "50a2afbdc678a65f-Others-permanent": "SVR", "50a2afbdc678a65f-Others-temporary": "KernelRidge", "51db62cb09adc2e8-Beans": "AdaBoostRegressor", "51db62cb09adc2e8-Cassava": "GaussianProcessRegressor", "51db62cb09adc2e8-Corn": "MLPRegressor", "51db62cb09adc2e8-Livestock": "Yhat_var", "51db62cb09adc2e8-Others-permanent": "Yhat_var", "51db62cb09adc2e8-Others-temporary": "GaussianProcessRegressor", "51db62cb09adc2e8-Rice": "DecisionTreeRegressor", "51db62cb09adc2e8-Soy": "PoissonRegressor", "5214b514b5b440be-A\u00e7a\u00ed": "AdaBoostRegressor", "5214b514b5b440be-Beans": "AdaBoostRegressor", "5214b514b5b440be-Cassava": "AdaBoostRegressor", "5214b514b5b440be-Corn": "Yhat_var", "5214b514b5b440be-Livestock": "Yhat_AutoReg", "5214b514b5b440be-Others-permanent": "Yhat_AutoReg", "5214b514b5b440be-Others-temporary": "AdaBoostRegressor", "5214b514b5b440be-Rice": "AdaBoostRegressor", "5214b514b5b440be-Soy": "AdaBoostRegressor", "56aa50429893f5ca-Beans": "GaussianProcessRegressor", "56aa50429893f5ca-Cassava": "AdaBoostRegressor", "56aa50429893f5ca-Corn": "PoissonRegressor", "56aa50429893f5ca-Livestock": "LinearSVR", "56aa50429893f5ca-Others-permanent": "LinearRegression", "56aa50429893f5ca-Others-temporary": "Yhat_var", "56aa50429893f5ca-Rice": "PassiveAggressiveRegressor", "588162e9cdf5d66d-A\u00e7a\u00ed": "AdaBoostRegressor", "588162e9cdf5d66d-Beans": "SVR", "588162e9cdf5d66d-Cassava": "DecisionTreeRegressor", "588162e9cdf5d66d-Corn": "TheilSenRegressor", "588162e9cdf5d66d-Livestock": "Yhat_var", "588162e9cdf5d66d-Others-permanent": "Yhat_sarimax", "588162e9cdf5d66d-Others-temporary": "DecisionTreeRegressor", "588162e9cdf5d66d-Rice": "Yhat_sarimax", "588162e9cdf5d66d-Sorghum": "AdaBoostRegressor", "588162e9cdf5d66d-Soy": "Yhat_var", "5b3728d86ce29fd2-A\u00e7a\u00ed": "GaussianProcessRegressor", "5b3728d86ce29fd2-Beans": "GaussianProcessRegressor", "5b3728d86ce29fd2-Cassava": "AdaBoostRegressor", "5b3728d86ce29fd2-Corn": "Yhat_autoarima", "5b3728d86ce29fd2-Livestock": "LinearSVR", "5b3728d86ce29fd2-Others-permanent": "Yhat_autoarima", "5b3728d86ce29fd2-Others-temporary": "GaussianProcessRegressor", "5b6072f8f6d37acc-A\u00e7a\u00ed": "MLPRegressor", "5b6072f8f6d37acc-Beans": "Yhat_autoarima", "5b6072f8f6d37acc-Cassava": "SVR", "5b6072f8f6d37acc-Cocoa": "AdaBoostRegressor", "5b6072f8f6d37acc-Corn": "DecisionTreeRegressor", "5b6072f8f6d37acc-Livestock": "Yhat_AutoReg", "5b6072f8f6d37acc-Others-permanent": "Yhat_autoarima", "5b6072f8f6d37acc-Others-temporary": "Yhat_AutoReg", "5b6072f8f6d37acc-Rice": "DecisionTreeRegressor", "5b6072f8f6d37acc-Soy": "AdaBoostRegressor", "5e1e131ec84f4c87-Beans": "NuSVR", "5e1e131ec84f4c87-Cassava": "PoissonRegressor", "5e1e131ec84f4c87-Corn": "MLPRegressor", "5e1e131ec84f4c87-Livestock": "Yhat_AutoReg", "5e1e131ec84f4c87-Others-permanent": "PassiveAggressiveRegressor", "5e1e131ec84f4c87-Others-temporary": "GaussianProcessRegressor", "5e1e131ec84f4c87-Rice": "GaussianProcessRegressor", "5e7093a1cd2a8779-Beans": "AdaBoostRegressor", "5e7093a1cd2a8779-Cassava": "TheilSenRegressor", "5e7093a1cd2a8779-Corn": "Yhat_AutoReg", "5e7093a1cd2a8779-Livestock": "BaggingRegressor", "5e7093a1cd2a8779-Others-permanent": "PassiveAggressiveRegressor", "5e7093a1cd2a8779-Others-temporary": "PoissonRegressor", "5e7093a1cd2a8779-Rice": "GaussianProcessRegressor", "60982e0f7928740a-A\u00e7a\u00ed": "GaussianProcessRegressor", "60982e0f7928740a-Beans": "BayesianRidge", "60982e0f7928740a-Cassava": "DecisionTreeRegressor", "60982e0f7928740a-Corn": "AdaBoostRegressor", "60982e0f7928740a-Livestock": "TweedieRegressor", "60982e0f7928740a-Others-permanent": "PoissonRegressor", "60982e0f7928740a-Others-temporary": "GaussianProcessRegressor", "60982e0f7928740a-Palm oil": "GaussianProcessRegressor", "617532f74ef8ed73-A\u00e7a\u00ed": "PassiveAggressiveRegressor", "617532f74ef8ed73-Beans": "NuSVR", "617532f74ef8ed73-Cassava": "KernelRidge", "617532f74ef8ed73-Cocoa": "Yhat_var", "617532f74ef8ed73-Corn": "PoissonRegressor", "617532f74ef8ed73-Livestock": "LinearSVR", "617532f74ef8ed73-Others-permanent": "AdaBoostRegressor", "617532f74ef8ed73-Others-temporary": "TheilSenRegressor", "617532f74ef8ed73-Rice": "PassiveAggressiveRegressor", "6471ede39ca61b39-A\u00e7a\u00ed": "Yhat_var", "6471ede39ca61b39-Cassava": "SVR", "6471ede39ca61b39-Cocoa": "AdaBoostRegressor", "6471ede39ca61b39-Corn": "AdaBoostRegressor", "6471ede39ca61b39-Livestock": "KernelRidge", "6471ede39ca61b39-Others-permanent": "NuSVR", "6471ede39ca61b39-Others-temporary": "PassiveAggressiveRegressor", "6471ede39ca61b39-Rice": "RandomForestRegressor", "64a227aa24370b17-Beans": "DecisionTreeRegressor", "64a227aa24370b17-Cassava": "BaggingRegressor", "64a227aa24370b17-Cocoa": "GaussianProcessRegressor", "64a227aa24370b17-Corn": "AdaBoostRegressor", "64a227aa24370b17-Livestock": "AdaBoostRegressor", "64a227aa24370b17-Others-permanent": "Yhat_autoarima", "64a227aa24370b17-Others-temporary": "DecisionTreeRegressor", "64a227aa24370b17-Rice": "DecisionTreeRegressor", "66fdcb391ed58d3d-Beans": "BaggingRegressor", "66fdcb391ed58d3d-Cassava": "GradientBoostingRegressor", "66fdcb391ed58d3d-Corn": "Yhat_autoarima", "66fdcb391ed58d3d-Livestock": "Yhat_AutoReg", "66fdcb391ed58d3d-Others-permanent": "HistGradientBoostingRegressor", "66fdcb391ed58d3d-Others-temporary": "BaggingRegressor", "68f01d67ad163f32-A\u00e7a\u00ed": "LinearSVR", "68f01d67ad163f32-Cassava": "PoissonRegressor", "68f01d67ad163f32-Cocoa": "Yhat_sarimax", "68f01d67ad163f32-Corn": "Yhat_sarimax", "68f01d67ad163f32-Livestock": "Yhat_sarimax", "68f01d67ad163f32-Others-permanent": "Yhat_var", "68f01d67ad163f32-Others-temporary": "AdaBoostRegressor", "68f01d67ad163f32-Rice": "Yhat_sarimax", "6a7b8c3ab2bc6c38-Beans": "SVR", "6a7b8c3ab2bc6c38-Cassava": "Yhat_AutoReg", "6a7b8c3ab2bc6c38-Corn": "OrthogonalMatchingPursuit", "6a7b8c3ab2bc6c38-Livestock": "Yhat_sarimax", "6a7b8c3ab2bc6c38-Others-permanent": "Yhat_autoarima", "6a7b8c3ab2bc6c38-Others-temporary": "GaussianProcessRegressor", "6cce2bf873870afc-A\u00e7a\u00ed": "PassiveAggressiveRegressor", "6cce2bf873870afc-Beans": "PoissonRegressor", "6cce2bf873870afc-Cassava": "DummyRegressor", "6cce2bf873870afc-Cocoa": "Yhat_var", "6cce2bf873870afc-Corn": "TheilSenRegressor", "6cce2bf873870afc-Livestock": "Lars", "6cce2bf873870afc-Others-permanent": "Yhat_sarimax", "6cce2bf873870afc-Others-temporary": "DecisionTreeRegressor", "6cce2bf873870afc-Palm oil": "KernelRidge", "6cce2bf873870afc-Rice": "PoissonRegressor", "6f911ef231b0efa7-Beans": "KernelRidge", "6f911ef231b0efa7-Cassava": "DecisionTreeRegressor", "6f911ef231b0efa7-Corn": "Yhat_AutoReg", "6f911ef231b0efa7-Livestock": "Yhat_var", "6f911ef231b0efa7-Others-permanent": "Yhat_AutoReg", "6f911ef231b0efa7-Others-temporary": "Yhat_autoarima", "6f911ef231b0efa7-Rice": "PoissonRegressor", "6f911ef231b0efa7-Soy": "PoissonRegressor", "70a4c62beba3c168-A\u00e7a\u00ed": "PassiveAggressiveRegressor", "70a4c62beba3c168-Beans": "GaussianProcessRegressor", "70a4c62beba3c168-Cassava": "BaggingRegressor", "70a4c62beba3c168-Cocoa": "NuSVR", "70a4c62beba3c168-Corn": "Yhat_AutoReg", "70a4c62beba3c168-Livestock": "Yhat_autoarima", "70a4c62beba3c168-Others-permanent": "BaggingRegressor", "70a4c62beba3c168-Others-temporary": "BayesianRidge", "70a4c62beba3c168-Palm oil": "AdaBoostRegressor", "70a4c62beba3c168-Rice": "Yhat_autoarima", "71975b563db10671-Beans": "Yhat_sarimax", "71975b563db10671-Cassava": "PoissonRegressor", "71975b563db10671-Cocoa": "AdaBoostRegressor", "71975b563db10671-Corn": "MLPRegressor", "71975b563db10671-Livestock": "BaggingRegressor", "71975b563db10671-Others-permanent": "Yhat_autoarima", "71975b563db10671-Others-temporary": "AdaBoostRegressor", "71975b563db10671-Rice": "Yhat_AutoReg", "72b65b337fc5302a-A\u00e7a\u00ed": "Yhat_var", "72b65b337fc5302a-Beans": "PassiveAggressiveRegressor", "72b65b337fc5302a-Cassava": "PoissonRegressor", "72b65b337fc5302a-Corn": "MLPRegressor", "72b65b337fc5302a-Livestock": "Yhat_autoarima", "72b65b337fc5302a-Others-permanent": "AdaBoostRegressor", "72b65b337fc5302a-Others-temporary": "Yhat_sarimax", "746cc42bfb8f6b62-Beans": "AdaBoostRegressor", "746cc42bfb8f6b62-Cassava": "Yhat_AutoReg", "746cc42bfb8f6b62-Corn": "AdaBoostRegressor", "746cc42bfb8f6b62-Livestock": "Yhat_var", "746cc42bfb8f6b62-Others-permanent": "GaussianProcessRegressor", "746cc42bfb8f6b62-Others-temporary": "AdaBoostRegressor", "746cc42bfb8f6b62-Rice": "BaggingRegressor", "74d75dde6dc4a5ec-A\u00e7a\u00ed": "GaussianProcessRegressor", "74d75dde6dc4a5ec-Beans": "RandomForestRegressor", "74d75dde6dc4a5ec-Cassava": "LinearSVR", "74d75dde6dc4a5ec-Corn": "DummyRegressor", "74d75dde6dc4a5ec-Livestock": "TheilSenRegressor", "74d75dde6dc4a5ec-Others-permanent": "MLPRegressor", "74d75dde6dc4a5ec-Others-temporary": "AdaBoostRegressor", "74d75dde6dc4a5ec-Rice": "AdaBoostRegressor", "764cd56389d50070-Beans": "AdaBoostRegressor", "764cd56389d50070-Cassava": "DecisionTreeRegressor", "764cd56389d50070-Corn": "NuSVR", "764cd56389d50070-Livestock": "Yhat_var", "764cd56389d50070-Others-permanent": "DecisionTreeRegressor", "764cd56389d50070-Others-temporary": "Yhat_autoarima", "764cd56389d50070-Rice": "Lars", "773cbe24d8fc9fea-Cassava": "PoissonRegressor", "773cbe24d8fc9fea-Livestock": "LinearSVR", "773cbe24d8fc9fea-Others-permanent": "BaggingRegressor", "773cbe24d8fc9fea-Others-temporary": "AdaBoostRegressor", "77c880feff17c521-A\u00e7a\u00ed": "AdaBoostRegressor", "77c880feff17c521-Beans": "AdaBoostRegressor", "77c880feff17c521-Cassava": "Yhat_var", "77c880feff17c521-Cocoa": "AdaBoostRegressor", "77c880feff17c521-Corn": "LinearSVR", "77c880feff17c521-Livestock": "Yhat_autoarima", "77c880feff17c521-Others-permanent": "MLPRegressor", "77c880feff17c521-Others-temporary": "Yhat_AutoReg", "77c880feff17c521-Rice": "PassiveAggressiveRegressor", "77c880feff17c521-Soy": "Yhat_var", "782568ced6ad8838-Beans": "PoissonRegressor", "782568ced6ad8838-Cassava": "DecisionTreeRegressor", "782568ced6ad8838-Cocoa": "Yhat_sarimax", "782568ced6ad8838-Corn": "PoissonRegressor", "782568ced6ad8838-Livestock": "Yhat_autoarima", "782568ced6ad8838-Others-permanent": "AdaBoostRegressor", "782568ced6ad8838-Others-temporary": "Yhat_sarimax", "782568ced6ad8838-Rice": "Yhat_sarimax", "782568ced6ad8838-Soy": "PoissonRegressor", "783dbed4df67af9f-Beans": "GaussianProcessRegressor", "783dbed4df67af9f-Cassava": "AdaBoostRegressor", "783dbed4df67af9f-Cocoa": "AdaBoostRegressor", "783dbed4df67af9f-Corn": "RandomForestRegressor", "783dbed4df67af9f-Livestock": "PoissonRegressor", "783dbed4df67af9f-Others-permanent": "Yhat_AutoReg", "783dbed4df67af9f-Others-temporary": "DummyRegressor", "783dbed4df67af9f-Rice": "AdaBoostRegressor", "783dbed4df67af9f-Soy": "Yhat_autoarima", "7926ffd2861f8dbc-Beans": "Yhat_sarimax", "7926ffd2861f8dbc-Cassava": "SVR", "7926ffd2861f8dbc-Cocoa": "Yhat_var", "7926ffd2861f8dbc-Corn": "AdaBoostRegressor", "7926ffd2861f8dbc-Livestock": "Yhat_AutoReg", "7926ffd2861f8dbc-Others-permanent": "Yhat_autoarima", "7926ffd2861f8dbc-Others-temporary": "Yhat_autoarima", "7926ffd2861f8dbc-Rice": "Yhat_autoarima", "7b95e27ce402e6e5-Beans": "AdaBoostRegressor", "7b95e27ce402e6e5-Cassava": "DecisionTreeRegressor", "7b95e27ce402e6e5-Corn": "KernelRidge", "7b95e27ce402e6e5-Livestock": "Yhat_sarimax", "7b95e27ce402e6e5-Others-permanent": "SVR", "7b95e27ce402e6e5-Others-temporary": "AdaBoostRegressor", "7b95e27ce402e6e5-Rice": "Yhat_sarimax", "7e56bd83460aabc7-A\u00e7a\u00ed": "AdaBoostRegressor", "7e56bd83460aabc7-Beans": "GaussianProcessRegressor", "7e56bd83460aabc7-Cassava": "KernelRidge", "7e56bd83460aabc7-Cocoa": "BaggingRegressor", "7e56bd83460aabc7-Corn": "DecisionTreeRegressor", "7e56bd83460aabc7-Livestock": "Yhat_AutoReg", "7e56bd83460aabc7-Others-permanent": "Yhat_autoarima", "7e56bd83460aabc7-Others-temporary": "MLPRegressor", "7e56bd83460aabc7-Rice": "MLPRegressor", "7f076b180f941ec8-Beans": "Yhat_autoarima", "7f076b180f941ec8-Cassava": "BaggingRegressor", "7f076b180f941ec8-Corn": "Yhat_sarimax", "7f076b180f941ec8-Livestock": "RandomForestRegressor", "7f076b180f941ec8-Others-permanent": "DecisionTreeRegressor", "7f076b180f941ec8-Others-temporary": "LinearRegression", "7f076b180f941ec8-Rice": "RandomForestRegressor", "7f076b180f941ec8-Soy": "PoissonRegressor", "807c5037e6993f2c-Beans": "DecisionTreeRegressor", "807c5037e6993f2c-Cassava": "Yhat_var", "807c5037e6993f2c-Corn": "Yhat_AutoReg", "807c5037e6993f2c-Livestock": "SVR", "807c5037e6993f2c-Others-permanent": "TheilSenRegressor", "807c5037e6993f2c-Others-temporary": "GaussianProcessRegressor", "807c5037e6993f2c-Rice": "AdaBoostRegressor", "807c5037e6993f2c-Soy": "Yhat_sarimax", "80e8ffb027590a74-A\u00e7a\u00ed": "MLPRegressor", "80e8ffb027590a74-Beans": "TransformedTargetRegressor", "80e8ffb027590a74-Cassava": "BaggingRegressor", "80e8ffb027590a74-Cocoa": "AdaBoostRegressor", "80e8ffb027590a74-Corn": "AdaBoostRegressor", "80e8ffb027590a74-Livestock": "Yhat_AutoReg", "80e8ffb027590a74-Others-permanent": "AdaBoostRegressor", "80e8ffb027590a74-Others-temporary": "Yhat_var", "80e8ffb027590a74-Rice": "BayesianRidge", "841ef18dcb3dbc3e-A\u00e7a\u00ed": "Yhat_var", "841ef18dcb3dbc3e-Beans": "Lars", "841ef18dcb3dbc3e-Cassava": "RandomForestRegressor", "841ef18dcb3dbc3e-Corn": "Yhat_autoarima", "841ef18dcb3dbc3e-Livestock": "TheilSenRegressor", "841ef18dcb3dbc3e-Others-permanent": "Yhat_AutoReg", "841ef18dcb3dbc3e-Others-temporary": "GaussianProcessRegressor", "841ef18dcb3dbc3e-Palm oil": "Yhat_autoarima", "855f882ce507aba5-A\u00e7a\u00ed": "AdaBoostRegressor", "855f882ce507aba5-Beans": "PassiveAggressiveRegressor", "855f882ce507aba5-Cassava": "Yhat_autoarima", "855f882ce507aba5-Cocoa": "DecisionTreeRegressor", "855f882ce507aba5-Corn": "MLPRegressor", "855f882ce507aba5-Livestock": "Yhat_AutoReg", "855f882ce507aba5-Others-permanent": "AdaBoostRegressor", "855f882ce507aba5-Others-temporary": "Yhat_AutoReg", "855f882ce507aba5-Rice": "RandomForestRegressor", "857b720c7c979ae1-A\u00e7a\u00ed": "MLPRegressor", "857b720c7c979ae1-Beans": "KernelRidge", "857b720c7c979ae1-Cassava": "PoissonRegressor", "857b720c7c979ae1-Corn": "TheilSenRegressor", "857b720c7c979ae1-Livestock": "Yhat_var", "857b720c7c979ae1-Others-permanent": "Yhat_AutoReg", "857b720c7c979ae1-Others-temporary": "AdaBoostRegressor", "857b720c7c979ae1-Rice": "Yhat_AutoReg", "85adcb13676b6172-Cassava": "AdaBoostRegressor", "85adcb13676b6172-Livestock": "DecisionTreeRegressor", "85adcb13676b6172-Others-permanent": "AdaBoostRegressor", "85adcb13676b6172-Others-temporary": "AdaBoostRegressor", "8683715784c40f0f-Livestock": "PassiveAggressiveRegressor", "86d92d4b0a058014-A\u00e7a\u00ed": "AdaBoostRegressor", "86d92d4b0a058014-Beans": "MLPRegressor", "86d92d4b0a058014-Cassava": "DecisionTreeRegressor", "86d92d4b0a058014-Corn": "MLPRegressor", "86d92d4b0a058014-Livestock": "AdaBoostRegressor", "86d92d4b0a058014-Others-permanent": "SVR", "86d92d4b0a058014-Others-temporary": "AdaBoostRegressor", "86d92d4b0a058014-Rice": "AdaBoostRegressor", "878bd5338ba55697-A\u00e7a\u00ed": "Yhat_autoarima", "878bd5338ba55697-Beans": "AdaBoostRegressor", "878bd5338ba55697-Cassava": "MLPRegressor", "878bd5338ba55697-Cocoa": "Yhat_sarimax", "878bd5338ba55697-Corn": "PoissonRegressor", "878bd5338ba55697-Livestock": "KernelRidge", "878bd5338ba55697-Others-permanent": "Yhat_sarimax", "878bd5338ba55697-Others-temporary": "DecisionTreeRegressor", "878bd5338ba55697-Rice": "GaussianProcessRegressor", "8910840651ee3971-A\u00e7a\u00ed": "AdaBoostRegressor", "8910840651ee3971-Beans": "DummyRegressor", "8910840651ee3971-Cassava": "TheilSenRegressor", "8910840651ee3971-Cocoa": "Yhat_autoarima", "8910840651ee3971-Corn": "RandomForestRegressor", "8910840651ee3971-Livestock": "Yhat_AutoReg", "8910840651ee3971-Others-permanent": "Yhat_sarimax", "8910840651ee3971-Others-temporary": "AdaBoostRegressor", "8910840651ee3971-Rice": "AdaBoostRegressor", "8a4ab531676691da-A\u00e7a\u00ed": "MLPRegressor", "8a4ab531676691da-Cassava": "Yhat_autoarima", "8a4ab531676691da-Corn": "AdaBoostRegressor", "8a4ab531676691da-Livestock": "AdaBoostRegressor", "8a4ab531676691da-Others-permanent": "NuSVR", "8a4ab531676691da-Others-temporary": "Yhat_sarimax", "8a4ab531676691da-Rice": "Yhat_AutoReg", "8a4ab531676691da-Soy": "PoissonRegressor", "8ca7766621b0ffe9-Beans": "DecisionTreeRegressor", "8ca7766621b0ffe9-Cassava": "Lars", "8ca7766621b0ffe9-Corn": "Yhat_var", "8ca7766621b0ffe9-Livestock": "Yhat_sarimax", "8ca7766621b0ffe9-Others-permanent": "DecisionTreeRegressor", "8ca7766621b0ffe9-Others-temporary": "Yhat_sarimax", "8ca7766621b0ffe9-Rice": "SVR", "8ca7766621b0ffe9-Soy": "Yhat_sarimax", "8e0eb10270d768f8-A\u00e7a\u00ed": "MLPRegressor", "8e0eb10270d768f8-Beans": "MLPRegressor", "8e0eb10270d768f8-Cassava": "Yhat_autoarima", "8e0eb10270d768f8-Corn": "SVR", "8e0eb10270d768f8-Livestock": "DecisionTreeRegressor", "8e0eb10270d768f8-Others-permanent": "Yhat_sarimax", "8e0eb10270d768f8-Others-temporary": "AdaBoostRegressor", "8e0eb10270d768f8-Rice": "Yhat_sarimax", "8e0eb10270d768f8-Soy": "Yhat_autoarima", "8ef25b4985bc557a-A\u00e7a\u00ed": "PassiveAggressiveRegressor", "8ef25b4985bc557a-Beans": "AdaBoostRegressor", "8ef25b4985bc557a-Cassava": "AdaBoostRegressor", "8ef25b4985bc557a-Cocoa": "Yhat_autoarima", "8ef25b4985bc557a-Corn": "Yhat_sarimax", "8ef25b4985bc557a-Livestock": "RandomForestRegressor", "8ef25b4985bc557a-Others-permanent": "AdaBoostRegressor", "8ef25b4985bc557a-Others-temporary": "AdaBoostRegressor", "8ef25b4985bc557a-Rice": "Yhat_sarimax", "902f3a9003f7e637-A\u00e7a\u00ed": "AdaBoostRegressor", "902f3a9003f7e637-Beans": "Yhat_autoarima", "902f3a9003f7e637-Cassava": "PoissonRegressor", "902f3a9003f7e637-Cocoa": "Yhat_AutoReg", "902f3a9003f7e637-Corn": "LinearSVR", "902f3a9003f7e637-Livestock": "Yhat_autoarima", "902f3a9003f7e637-Others-permanent": "SVR", "902f3a9003f7e637-Others-temporary": "PoissonRegressor", "902f3a9003f7e637-Palm oil": "PassiveAggressiveRegressor", "902f3a9003f7e637-Rice": "AdaBoostRegressor", "93656feaf53efbef-A\u00e7a\u00ed": "MLPRegressor", "93656feaf53efbef-Beans": "Yhat_sarimax", "93656feaf53efbef-Cassava": "AdaBoostRegressor", "93656feaf53efbef-Corn": "Yhat_AutoReg", "93656feaf53efbef-Livestock": "TransformedTargetRegressor", "93656feaf53efbef-Others-permanent": "TheilSenRegressor", "93656feaf53efbef-Others-temporary": "GaussianProcessRegressor", "93656feaf53efbef-Palm oil": "SVR", "960b4f2c94a2fb2c-A\u00e7a\u00ed": "AdaBoostRegressor", "960b4f2c94a2fb2c-Beans": "DecisionTreeRegressor", "960b4f2c94a2fb2c-Cassava": "Yhat_autoarima", "960b4f2c94a2fb2c-Cocoa": "AdaBoostRegressor", "960b4f2c94a2fb2c-Corn": "BayesianRidge", "960b4f2c94a2fb2c-Livestock": "Yhat_sarimax", "960b4f2c94a2fb2c-Others-permanent": "Yhat_autoarima", "960b4f2c94a2fb2c-Others-temporary": "PassiveAggressiveRegressor", "960b4f2c94a2fb2c-Palm oil": "Yhat_var", "960b4f2c94a2fb2c-Rice": "Yhat_AutoReg", "9bc907eeb9e3fc52-Cassava": "TheilSenRegressor", "9bc907eeb9e3fc52-Corn": "SVR", "9bc907eeb9e3fc52-Livestock": "Yhat_autoarima", "9bc907eeb9e3fc52-Others-permanent": "Yhat_autoarima", "9bc907eeb9e3fc52-Others-temporary": "AdaBoostRegressor", "9bd4f108a319de42-A\u00e7a\u00ed": "Yhat_var", "9bd4f108a319de42-Cassava": "PassiveAggressiveRegressor", "9bd4f108a319de42-Livestock": "LinearSVR", "9bd4f108a319de42-Others-permanent": "NuSVR", "9bd4f108a319de42-Others-temporary": "KernelRidge", "9bd4f108a319de42-Rice": "AdaBoostRegressor", "9ce50fa197613de1-A\u00e7a\u00ed": "MLPRegressor", "9ce50fa197613de1-Beans": "BayesianRidge", "9ce50fa197613de1-Cassava": "Yhat_AutoReg", "9ce50fa197613de1-Corn": "AdaBoostRegressor", "9ce50fa197613de1-Livestock": "Yhat_AutoReg", "9ce50fa197613de1-Others-permanent": "LassoLars", "9ce50fa197613de1-Others-temporary": "GaussianProcessRegressor", "9d8776ac0a78d908-A\u00e7a\u00ed": "LinearSVR", "9d8776ac0a78d908-Cassava": "NuSVR", "9d8776ac0a78d908-Livestock": "KernelRidge", "9d8776ac0a78d908-Others-permanent": "BaggingRegressor", "9d8776ac0a78d908-Others-temporary": "GaussianProcessRegressor", "a18af8fbae254d86-Beans": "AdaBoostRegressor", "a18af8fbae254d86-Cassava": "LinearSVR", "a18af8fbae254d86-Corn": "Yhat_sarimax", "a18af8fbae254d86-Livestock": "PoissonRegressor", "a18af8fbae254d86-Others-permanent": "AdaBoostRegressor", "a18af8fbae254d86-Others-temporary": "AdaBoostRegressor", "a1b03f0e4d79b4fe-A\u00e7a\u00ed": "MLPRegressor", "a1b03f0e4d79b4fe-Beans": "DecisionTreeRegressor", "a1b03f0e4d79b4fe-Cassava": "NuSVR", "a1b03f0e4d79b4fe-Cocoa": "AdaBoostRegressor", "a1b03f0e4d79b4fe-Corn": "SVR", "a1b03f0e4d79b4fe-Livestock": "SVR", "a1b03f0e4d79b4fe-Others-permanent": "DummyRegressor", "a1b03f0e4d79b4fe-Others-temporary": "KernelRidge", "a1b03f0e4d79b4fe-Rice": "AdaBoostRegressor", "a245de687a867003-A\u00e7a\u00ed": "PassiveAggressiveRegressor", "a245de687a867003-Cassava": "AdaBoostRegressor", "a245de687a867003-Livestock": "Yhat_sarimax", "a245de687a867003-Others-permanent": "AdaBoostRegressor", "a245de687a867003-Others-temporary": "AdaBoostRegressor", "a454a6655aaaaaed-A\u00e7a\u00ed": "MLPRegressor", "a454a6655aaaaaed-Beans": "Yhat_autoarima", "a454a6655aaaaaed-Cassava": "LinearRegression", "a454a6655aaaaaed-Corn": "AdaBoostRegressor", "a454a6655aaaaaed-Livestock": "LinearSVR", "a454a6655aaaaaed-Others-permanent": "BaggingRegressor", "a454a6655aaaaaed-Others-temporary": "GaussianProcessRegressor", "a454a6655aaaaaed-Palm oil": "Yhat_var", "a4d1e1ff1bc3b830-Beans": "MLPRegressor", "a4d1e1ff1bc3b830-Cassava": "MLPRegressor", "a4d1e1ff1bc3b830-Corn": "PassiveAggressiveRegressor", "a4d1e1ff1bc3b830-Livestock": "Yhat_AutoReg", "a4d1e1ff1bc3b830-Others-permanent": "PassiveAggressiveRegressor", "a4d1e1ff1bc3b830-Others-temporary": "GaussianProcessRegressor", "a4d1e1ff1bc3b830-Palm oil": "PoissonRegressor", "a51be58f39d1d625-A\u00e7a\u00ed": "GaussianProcessRegressor", "a51be58f39d1d625-Beans": "PassiveAggressiveRegressor", "a51be58f39d1d625-Cassava": "AdaBoostRegressor", "a51be58f39d1d625-Corn": "GradientBoostingRegressor", "a51be58f39d1d625-Livestock": "PassiveAggressiveRegressor", "a51be58f39d1d625-Others-permanent": "AdaBoostRegressor", "a51be58f39d1d625-Others-temporary": "PassiveAggressiveRegressor", "a51be58f39d1d625-Rice": "LinearRegression", "a7187a1b5b870cf4-Livestock": "Yhat_AutoReg", "a7187a1b5b870cf4-Others-permanent": "AdaBoostRegressor", "a7187a1b5b870cf4-Others-temporary": "AdaBoostRegressor", "ab984377b2dc0284-A\u00e7a\u00ed": "AdaBoostRegressor", "ab984377b2dc0284-Beans": "DecisionTreeRegressor", "ab984377b2dc0284-Cassava": "Yhat_sarimax", "ab984377b2dc0284-Cocoa": "GaussianProcessRegressor", "ab984377b2dc0284-Corn": "Yhat_autoarima", "ab984377b2dc0284-Livestock": "Yhat_AutoReg", "ab984377b2dc0284-Others-permanent": "Yhat_var", "ab984377b2dc0284-Others-temporary": "Yhat_sarimax", "abcadd700f8948e3-Beans": "Yhat_sarimax", "abcadd700f8948e3-Cassava": "Yhat_var", "abcadd700f8948e3-Corn": "BaggingRegressor", "abcadd700f8948e3-Livestock": "Yhat_AutoReg", "abcadd700f8948e3-Others-permanent": "DummyRegressor", "abcadd700f8948e3-Others-temporary": "GaussianProcessRegressor", "abcadd700f8948e3-Rice": "PoissonRegressor", "ad622472210b0b57-A\u00e7a\u00ed": "MLPRegressor", "ad622472210b0b57-Beans": "TheilSenRegressor", "ad622472210b0b57-Cassava": "KernelRidge", "ad622472210b0b57-Corn": "Yhat_AutoReg", "ad622472210b0b57-Livestock": "Yhat_autoarima", "ad622472210b0b57-Others-permanent": "SVR", "ad622472210b0b57-Others-temporary": "DecisionTreeRegressor", "ad622472210b0b57-Rice": "PoissonRegressor", "ae345f007f327b22-A\u00e7a\u00ed": "AdaBoostRegressor", "ae345f007f327b22-Beans": "Yhat_var", "ae345f007f327b22-Cassava": "PoissonRegressor", "ae345f007f327b22-Cocoa": "KernelRidge", "ae345f007f327b22-Corn": "Yhat_autoarima", "ae345f007f327b22-Livestock": "Yhat_AutoReg", "ae345f007f327b22-Others-permanent": "Yhat_var", "ae345f007f327b22-Others-temporary": "LassoLarsIC", "ae345f007f327b22-Rice": "Yhat_sarimax", "b0e4b4b27117562a-Beans": "RandomForestRegressor", "b0e4b4b27117562a-Cassava": "GaussianProcessRegressor", "b0e4b4b27117562a-Cocoa": "Yhat_sarimax", "b0e4b4b27117562a-Corn": "AdaBoostRegressor", "b0e4b4b27117562a-Livestock": "BaggingRegressor", "b0e4b4b27117562a-Others-permanent": "MLPRegressor", "b0e4b4b27117562a-Others-temporary": "AdaBoostRegressor", "b0e4b4b27117562a-Rice": "DecisionTreeRegressor", "b4829f1e221d9778-A\u00e7a\u00ed": "AdaBoostRegressor", "b4829f1e221d9778-Beans": "AdaBoostRegressor", "b4829f1e221d9778-Cassava": "AdaBoostRegressor", "b4829f1e221d9778-Corn": "Yhat_sarimax", "b4829f1e221d9778-Livestock": "KernelRidge", "b4829f1e221d9778-Others-permanent": "AdaBoostRegressor", "b4829f1e221d9778-Others-temporary": "LinearSVR", "b4829f1e221d9778-Rice": "Yhat_autoarima", "b4bb04d2a6472ea0-A\u00e7a\u00ed": "AdaBoostRegressor", "b4bb04d2a6472ea0-Beans": "GaussianProcessRegressor", "b4bb04d2a6472ea0-Cassava": "DecisionTreeRegressor", "b4bb04d2a6472ea0-Corn": "SVR", "b4bb04d2a6472ea0-Livestock": "Yhat_var", "b4bb04d2a6472ea0-Others-permanent": "TheilSenRegressor", "b4bb04d2a6472ea0-Others-temporary": "PoissonRegressor", "b73e63cd3a2904c9-Beans": "GaussianProcessRegressor", "b73e63cd3a2904c9-Cassava": "KernelRidge", "b73e63cd3a2904c9-Corn": "MLPRegressor", "b73e63cd3a2904c9-Livestock": "Yhat_autoarima", "b73e63cd3a2904c9-Others-permanent": "GaussianProcessRegressor", "b73e63cd3a2904c9-Others-temporary": "Yhat_autoarima", "b73e63cd3a2904c9-Rice": "BaggingRegressor", "ba23b66825fc1c91-A\u00e7a\u00ed": "MLPRegressor", "ba23b66825fc1c91-Beans": "Yhat_AutoReg", "ba23b66825fc1c91-Cassava": "OrthogonalMatchingPursuit", "ba23b66825fc1c91-Corn": "TransformedTargetRegressor", "ba23b66825fc1c91-Livestock": "PoissonRegressor", "ba23b66825fc1c91-Others-permanent": "PoissonRegressor", "ba23b66825fc1c91-Others-temporary": "Yhat_var", "ba23b66825fc1c91-Rice": "MLPRegressor", "ba4547c678a9a2e6-A\u00e7a\u00ed": "GaussianProcessRegressor", "ba4547c678a9a2e6-Beans": "Yhat_autoarima", "ba4547c678a9a2e6-Cassava": "PassiveAggressiveRegressor", "ba4547c678a9a2e6-Corn": "Yhat_var", "ba4547c678a9a2e6-Livestock": "TweedieRegressor", "ba4547c678a9a2e6-Others-permanent": "Yhat_var", "ba4547c678a9a2e6-Others-temporary": "AdaBoostRegressor", "ba4547c678a9a2e6-Palm oil": "Yhat_var", "bce36d2f8aa39d8b-Beans": "DecisionTreeRegressor", "bce36d2f8aa39d8b-Cassava": "DecisionTreeRegressor", "bce36d2f8aa39d8b-Cocoa": "Yhat_autoarima", "bce36d2f8aa39d8b-Corn": "PassiveAggressiveRegressor", "bce36d2f8aa39d8b-Livestock": "TheilSenRegressor", "bce36d2f8aa39d8b-Others-permanent": "Yhat_autoarima", "bce36d2f8aa39d8b-Others-temporary": "AdaBoostRegressor", "bce36d2f8aa39d8b-Rice": "GaussianProcessRegressor", "bce36d2f8aa39d8b-Soy": "Yhat_autoarima", "be4424aa54f8d2ae-A\u00e7a\u00ed": "AdaBoostRegressor", "be4424aa54f8d2ae-Beans": "AdaBoostRegressor", "be4424aa54f8d2ae-Cassava": "BaggingRegressor", "be4424aa54f8d2ae-Cocoa": "AdaBoostRegressor", "be4424aa54f8d2ae-Corn": "Yhat_autoarima", "be4424aa54f8d2ae-Livestock": "Yhat_AutoReg", "be4424aa54f8d2ae-Others-permanent": "Yhat_autoarima", "be4424aa54f8d2ae-Others-temporary": "MLPRegressor", "be4424aa54f8d2ae-Palm oil": "BaggingRegressor", "be4424aa54f8d2ae-Rice": "AdaBoostRegressor", "be4424aa54f8d2ae-Soy": "Yhat_var", "be8a37473dc63db0-A\u00e7a\u00ed": "AdaBoostRegressor", "be8a37473dc63db0-Beans": "MLPRegressor", "be8a37473dc63db0-Cassava": "TheilSenRegressor", "be8a37473dc63db0-Cocoa": "Yhat_autoarima", "be8a37473dc63db0-Corn": "PoissonRegressor", "be8a37473dc63db0-Livestock": "Yhat_autoarima", "be8a37473dc63db0-Others-permanent": "Yhat_var", "be8a37473dc63db0-Others-temporary": "AdaBoostRegressor", "be8a37473dc63db0-Rice": "MLPRegressor", "be8a37473dc63db0-Soy": "NuSVR", "c0019c9a4b4819f2-A\u00e7a\u00ed": "PassiveAggressiveRegressor", "c0019c9a4b4819f2-Beans": "GradientBoostingRegressor", "c0019c9a4b4819f2-Cassava": "Yhat_autoarima", "c0019c9a4b4819f2-Cocoa": "DummyRegressor", "c0019c9a4b4819f2-Corn": "DecisionTreeRegressor", "c0019c9a4b4819f2-Livestock": "SVR", "c0019c9a4b4819f2-Others-permanent": "Yhat_var", "c0019c9a4b4819f2-Others-temporary": "AdaBoostRegressor", "c118b149223ba711-Cassava": "PassiveAggressiveRegressor", "c118b149223ba711-Livestock": "PoissonRegressor", "c118b149223ba711-Others-permanent": "LassoLars", "c118b149223ba711-Others-temporary": "MLPRegressor", "c129d0cd5f1afd51-A\u00e7a\u00ed": "PassiveAggressiveRegressor", "c129d0cd5f1afd51-Beans": "PassiveAggressiveRegressor", "c129d0cd5f1afd51-Cassava": "PassiveAggressiveRegressor", "c129d0cd5f1afd51-Cocoa": "BaggingRegressor", "c129d0cd5f1afd51-Corn": "AdaBoostRegressor", "c129d0cd5f1afd51-Livestock": "Yhat_autoarima", "c129d0cd5f1afd51-Others-permanent": "LinearSVR", "c129d0cd5f1afd51-Others-temporary": "AdaBoostRegressor", "c129d0cd5f1afd51-Rice": "TheilSenRegressor", "c45d8ddba643c0d7-A\u00e7a\u00ed": "AdaBoostRegressor", "c45d8ddba643c0d7-Cassava": "Yhat_autoarima", "c45d8ddba643c0d7-Livestock": "TheilSenRegressor", "c45d8ddba643c0d7-Others-permanent": "Yhat_var", "c45d8ddba643c0d7-Others-temporary": "BaggingRegressor", "c45d8ddba643c0d7-Palm oil": "Yhat_AutoReg", "cb23149538de1c42-Beans": "PoissonRegressor", "cb23149538de1c42-Cassava": "KernelRidge", "cb23149538de1c42-Corn": "PassiveAggressiveRegressor", "cb23149538de1c42-Livestock": "Yhat_AutoReg", "cb23149538de1c42-Others-permanent": "PoissonRegressor", "cb23149538de1c42-Others-temporary": "Yhat_var", "cb23149538de1c42-Rice": "Yhat_sarimax", "cdc89121a4b9478b-Beans": "BaggingRegressor", "cdc89121a4b9478b-Cassava": "KernelRidge", "cdc89121a4b9478b-Corn": "Yhat_var", "cdc89121a4b9478b-Livestock": "GradientBoostingRegressor", "cdc89121a4b9478b-Others-permanent": "TransformedTargetRegressor", "cdc89121a4b9478b-Others-temporary": "KernelRidge", "cdc89121a4b9478b-Rice": "Yhat_var", "cdc89121a4b9478b-Soy": "Yhat_AutoReg", "cead2cbd1f8f0b86-A\u00e7a\u00ed": "MLPRegressor", "cead2cbd1f8f0b86-Beans": "Yhat_AutoReg", "cead2cbd1f8f0b86-Cassava": "SVR", "cead2cbd1f8f0b86-Corn": "AdaBoostRegressor", "cead2cbd1f8f0b86-Livestock": "Yhat_AutoReg", "cead2cbd1f8f0b86-Others-permanent": "LassoLarsIC", "cead2cbd1f8f0b86-Others-temporary": "NuSVR", "cead2cbd1f8f0b86-Rice": "Yhat_arima", "cead2cbd1f8f0b86-Soy": "MLPRegressor", "cf96db4cc35ea025-Livestock": "PassiveAggressiveRegressor", "cf96db4cc35ea025-Others-permanent": "AdaBoostRegressor", "cf96db4cc35ea025-Others-temporary": "AdaBoostRegressor", "d0f5f5b9fcecb0d8-Beans": "AdaBoostRegressor", "d0f5f5b9fcecb0d8-Cassava": "AdaBoostRegressor", "d0f5f5b9fcecb0d8-Corn": "AdaBoostRegressor", "d0f5f5b9fcecb0d8-Livestock": "KernelRidge", "d0f5f5b9fcecb0d8-Others-permanent": "GaussianProcessRegressor", "d0f5f5b9fcecb0d8-Others-temporary": "Yhat_autoarima", "d0f5f5b9fcecb0d8-Palm oil": "AdaBoostRegressor", "d0f5f5b9fcecb0d8-Rice": "AdaBoostRegressor", "d42d0e216f57b2ae-A\u00e7a\u00ed": "PassiveAggressiveRegressor", "d42d0e216f57b2ae-Cassava": "Yhat_var", "d42d0e216f57b2ae-Corn": "Yhat_var", "d42d0e216f57b2ae-Livestock": "Yhat_AutoReg", "d42d0e216f57b2ae-Others-permanent": "TransformedTargetRegressor", "d42d0e216f57b2ae-Others-temporary": "OrthogonalMatchingPursuit", "d6f1f98b1745e004-Beans": "AdaBoostRegressor", "d6f1f98b1745e004-Cassava": "GaussianProcessRegressor", "d6f1f98b1745e004-Cocoa": "LinearSVR", "d6f1f98b1745e004-Corn": "AdaBoostRegressor", "d6f1f98b1745e004-Livestock": "Yhat_AutoReg", "d6f1f98b1745e004-Others-permanent": "BaggingRegressor", "d6f1f98b1745e004-Others-temporary": "BaggingRegressor", "d6f1f98b1745e004-Rice": "MLPRegressor", "d6ffd6d7dfe22d57-A\u00e7a\u00ed": "PassiveAggressiveRegressor", "d6ffd6d7dfe22d57-Beans": "MLPRegressor", "d6ffd6d7dfe22d57-Cassava": "LinearSVR", "d6ffd6d7dfe22d57-Corn": "Yhat_var", "d6ffd6d7dfe22d57-Livestock": "PassiveAggressiveRegressor", "d6ffd6d7dfe22d57-Others-permanent": "SVR", "d6ffd6d7dfe22d57-Others-temporary": "GaussianProcessRegressor", "d6ffd6d7dfe22d57-Rice": "MLPRegressor", "de1994d393ef525a-Beans": "BaggingRegressor", "de1994d393ef525a-Cassava": "Yhat_autoarima", "de1994d393ef525a-Cocoa": "AdaBoostRegressor", "de1994d393ef525a-Corn": "Yhat_AutoReg", "de1994d393ef525a-Livestock": "BaggingRegressor", "de1994d393ef525a-Others-permanent": "NuSVR", "de1994d393ef525a-Others-temporary": "SVR", "de1994d393ef525a-Rice": "AdaBoostRegressor", "df19203419d2ea64-A\u00e7a\u00ed": "TheilSenRegressor", "df19203419d2ea64-Beans": "AdaBoostRegressor", "df19203419d2ea64-Cassava": "KernelRidge", "df19203419d2ea64-Cocoa": "AdaBoostRegressor", "df19203419d2ea64-Corn": "KernelRidge", "df19203419d2ea64-Livestock": "LinearSVR", "df19203419d2ea64-Others-permanent": "AdaBoostRegressor", "df19203419d2ea64-Others-temporary": "GaussianProcessRegressor", "df19203419d2ea64-Rice": "AdaBoostRegressor", "df2cd1cbe849ebd0-A\u00e7a\u00ed": "MLPRegressor", "df2cd1cbe849ebd0-Beans": "PassiveAggressiveRegressor", "df2cd1cbe849ebd0-Cassava": "SVR", "df2cd1cbe849ebd0-Corn": "AdaBoostRegressor", "df2cd1cbe849ebd0-Livestock": "Yhat_autoarima", "df2cd1cbe849ebd0-Others-permanent": "Yhat_var", "df2cd1cbe849ebd0-Others-temporary": "GaussianProcessRegressor", "df2cd1cbe849ebd0-Palm oil": "Yhat_var", "e635f6b0f8a98808-Beans": "Yhat_var", "e635f6b0f8a98808-Cassava": "Yhat_var", "e635f6b0f8a98808-Cocoa": "AdaBoostRegressor", "e635f6b0f8a98808-Corn": "RandomForestRegressor", "e635f6b0f8a98808-Livestock": "TheilSenRegressor", "e635f6b0f8a98808-Others-permanent": "LinearSVR", "e635f6b0f8a98808-Others-temporary": "Lars", "e635f6b0f8a98808-Rice": "KernelRidge", "eac302b92f87d9ca-A\u00e7a\u00ed": "PassiveAggressiveRegressor", "eac302b92f87d9ca-Beans": "DecisionTreeRegressor", "eac302b92f87d9ca-Cassava": "PoissonRegressor", "eac302b92f87d9ca-Cocoa": "AdaBoostRegressor", "eac302b92f87d9ca-Corn": "DecisionTreeRegressor", "eac302b92f87d9ca-Livestock": "PoissonRegressor", "eac302b92f87d9ca-Others-permanent": "LinearRegression", "eac302b92f87d9ca-Others-temporary": "TheilSenRegressor", "eac302b92f87d9ca-Rice": "TheilSenRegressor", "ec84c1e86735dc9b-A\u00e7a\u00ed": "MLPRegressor", "ec84c1e86735dc9b-Beans": "MLPRegressor", "ec84c1e86735dc9b-Cassava": "DecisionTreeRegressor", "ec84c1e86735dc9b-Corn": "TheilSenRegressor", "ec84c1e86735dc9b-Livestock": "BaggingRegressor", "ec84c1e86735dc9b-Others-permanent": "KernelRidge", "ec84c1e86735dc9b-Others-temporary": "PoissonRegressor", "ec84c1e86735dc9b-Rice": "Yhat_var", "f1fd357c5adaa8dc-A\u00e7a\u00ed": "AdaBoostRegressor", "f1fd357c5adaa8dc-Beans": "LinearSVR", "f1fd357c5adaa8dc-Cassava": "AdaBoostRegressor", "f1fd357c5adaa8dc-Cocoa": "AdaBoostRegressor", "f1fd357c5adaa8dc-Corn": "Yhat_sarimax", "f1fd357c5adaa8dc-Livestock": "BaggingRegressor", "f1fd357c5adaa8dc-Others-permanent": "GradientBoostingRegressor", "f1fd357c5adaa8dc-Others-temporary": "AdaBoostRegressor", "f1fd357c5adaa8dc-Rice": "AdaBoostRegressor", "f39d21744916469c-A\u00e7a\u00ed": "AdaBoostRegressor", "f39d21744916469c-Cassava": "Yhat_var", "f39d21744916469c-Corn": "KernelRidge", "f39d21744916469c-Livestock": "AdaBoostRegressor", "f39d21744916469c-Others-permanent": "Yhat_var", "f39d21744916469c-Others-temporary": "PassiveAggressiveRegressor", "f3c2cc112eb0e6fe-Beans": "LassoLars", "f3c2cc112eb0e6fe-Cassava": "TransformedTargetRegressor", "f3c2cc112eb0e6fe-Corn": "PassiveAggressiveRegressor", "f3c2cc112eb0e6fe-Livestock": "Yhat_sarimax", "f3c2cc112eb0e6fe-Others-permanent": "Yhat_AutoReg", "f3c2cc112eb0e6fe-Others-temporary": "BaggingRegressor", "f3c2cc112eb0e6fe-Rice": "GaussianProcessRegressor", "f4612b8b5a8223b5-Beans": "AdaBoostRegressor", "f4612b8b5a8223b5-Cassava": "Lars", "f4612b8b5a8223b5-Corn": "AdaBoostRegressor", "f4612b8b5a8223b5-Livestock": "Yhat_AutoReg", "f4612b8b5a8223b5-Others-permanent": "KernelRidge", "f4612b8b5a8223b5-Others-temporary": "AdaBoostRegressor", "f67358b81451a8d1-A\u00e7a\u00ed": "MLPRegressor", "f67358b81451a8d1-Cassava": "DecisionTreeRegressor", "f67358b81451a8d1-Livestock": "KernelRidge", "f67358b81451a8d1-Others-permanent": "Yhat_autoarima", "f67358b81451a8d1-Others-temporary": "LassoLars", "f8e70145d73bd728-A\u00e7a\u00ed": "LinearSVR", "f8e70145d73bd728-Beans": "GaussianProcessRegressor", "f8e70145d73bd728-Cassava": "AdaBoostRegressor", "f8e70145d73bd728-Cocoa": "BaggingRegressor", "f8e70145d73bd728-Livestock": "Yhat_autoarima", "f8e70145d73bd728-Others-permanent": "Yhat_autoarima", "f8e70145d73bd728-Others-temporary": "GaussianProcessRegressor", "fa005e1ffef6032a-A\u00e7a\u00ed": "Yhat_var", "fa005e1ffef6032a-Cassava": "BaggingRegressor", "fa005e1ffef6032a-Corn": "Yhat_sarimax", "fa005e1ffef6032a-Livestock": "KernelRidge", "fa005e1ffef6032a-Others-permanent": "AdaBoostRegressor", "fa005e1ffef6032a-Others-temporary": "BaggingRegressor", "fae378a53734da72-Beans": "BaggingRegressor", "fae378a53734da72-Cassava": "AdaBoostRegressor", "fae378a53734da72-Cocoa": "Yhat_var", "fae378a53734da72-Corn": "LinearSVR", "fae378a53734da72-Livestock": "Yhat_sarimax", "fae378a53734da72-Others-permanent": "SVR", "fae378a53734da72-Others-temporary": "Yhat_autoarima", "fae378a53734da72-Rice": "AdaBoostRegressor", "fda49275fbf5caf6-A\u00e7a\u00ed": "TheilSenRegressor", "fda49275fbf5caf6-Beans": "PassiveAggressiveRegressor", "fda49275fbf5caf6-Cassava": "Yhat_var", "fda49275fbf5caf6-Cocoa": "AdaBoostRegressor", "fda49275fbf5caf6-Corn": "DummyRegressor", "fda49275fbf5caf6-Livestock": "Yhat_sarimax", "fda49275fbf5caf6-Others-permanent": "DecisionTreeRegressor", "fda49275fbf5caf6-Others-temporary": "BayesianRidge"}